{
  "main": {
    "id": "201367eacb69d189",
    "type": "split",
    "children": [
      {
        "id": "9de8fdeae96893f1",
        "type": "tabs",
        "children": [
          {
            "id": "2a4d6b6327042121",
            "type": "leaf",
            "state": {
              "type": "markdown",
              "state": {
                "file": "项目/开放实验Zeto.md",
                "mode": "source",
                "source": false
              },
              "icon": "lucide-file",
              "title": "开放实验Zeto"
            }
          }
        ]
      }
    ],
    "direction": "vertical"
  },
  "left": {
    "id": "a837119ca631d6e1",
    "type": "split",
    "children": [
      {
        "id": "533f1d8cbe2b10d1",
        "type": "tabs",
        "children": [
          {
            "id": "7a3dee57a4518add",
            "type": "leaf",
            "state": {
              "type": "file-explorer",
              "state": {
                "sortOrder": "alphabetical"
              },
              "icon": "lucide-folder-closed",
              "title": "文件列表"
            }
          },
          {
            "id": "e3fdfef1d179e35f",
            "type": "leaf",
            "state": {
              "type": "search",
              "state": {
                "query": "calloc",
                "matchingCase": false,
                "explainSearch": false,
                "collapseAll": false,
                "extraContext": false,
                "sortOrder": "alphabetical"
              },
              "icon": "lucide-search",
              "title": "搜索"
            }
          },
          {
            "id": "8c65c8d02c7b16a4",
            "type": "leaf",
            "state": {
              "type": "bookmarks",
              "state": {},
              "icon": "lucide-bookmark",
              "title": "书签"
            }
          }
        ]
      }
    ],
    "direction": "horizontal",
    "width": 223.51103591918945
  },
  "right": {
    "id": "efa81811cf5e4789",
    "type": "split",
    "children": [
      {
        "id": "e633e6a621cb613f",
        "type": "tabs",
        "children": [
          {
            "id": "162e003f4300a95e",
            "type": "leaf",
            "state": {
              "type": "git-view",
              "state": {},
              "icon": "git-pull-request",
              "title": "Source Control"
            }
          },
          {
            "id": "9e29a52a585c7e63",
            "type": "leaf",
            "state": {
              "type": "outline",
              "state": {
                "file": "C语言/0. 面向考试的C语言不完全指北.md"
              },
              "icon": "lucide-list",
              "title": "0. 面向考试的C语言不完全指北 的大纲"
            }
          },
          {
            "id": "ec864ed686c524fb",
            "type": "leaf",
            "state": {
              "type": "backlink",
              "state": {
                "file": "pytorch/附件/池化层.png",
                "collapseAll": false,
                "extraContext": false,
                "sortOrder": "alphabetical",
                "showSearch": false,
                "searchQuery": "",
                "backlinkCollapsed": false,
                "unlinkedCollapsed": true
              },
              "icon": "links-coming-in",
              "title": "池化层 的反向链接列表"
            }
          },
          {
            "id": "bba1ce07a58d8cc0",
            "type": "leaf",
            "state": {
              "type": "outgoing-link",
              "state": {
                "file": "pytorch/Pytorch基础--以MINIST手写识别为例.md",
                "linksCollapsed": false,
                "unlinkedCollapsed": true
              },
              "icon": "links-going-out",
              "title": "Pytorch基础--以MINIST手写识别为例 的出链列表"
            }
          },
          {
            "id": "3ee3ffcf306263af",
            "type": "leaf",
            "state": {
              "type": "tag",
              "state": {
                "sortOrder": "frequency",
                "useHierarchy": true
              },
              "icon": "lucide-tags",
              "title": "标签"
            }
          }
        ]
      }
    ],
    "direction": "horizontal",
    "width": 315.5
  },
  "left-ribbon": {
    "hiddenItems": {
      "switcher:打开快速切换": false,
      "graph:查看关系图谱": false,
      "canvas:新建白板": false,
      "daily-notes:打开/创建今天的日记": false,
      "templates:插入模板": false,
      "command-palette:打开命令面板": false,
      "obsidian-git:Open Git source control": false
    }
  },
  "active": "2a4d6b6327042121",
  "lastOpenFiles": [
    "论文/会议.md",
    "项目/开放实验Zeto.md",
    "数据分析/回归技术Regression Technique.md",
    "数据分析/支持向量机Support Vector Machine.md",
    "杂记/杂记menu.md",
    "杂记/番茄工作法Pomodoro Technique.md",
    "数据分析",
    "项目",
    "论文/基础知识.md",
    "C语言/13. 树.md",
    "C语言/11. 线性表的链式存储.md",
    "C语言/9. 数据结构概述.md",
    "C语言/15. 排序.md",
    "面向对象程序设计/面向对象程序设计.md",
    "计算机视觉/计算机视觉.md",
    "C语言/0. 面向考试的C语言不完全指北.md",
    "论文/An_Elevator_Advertisement_Recommendation_System_Design_based_on_Machine_Vision_and_Deep_Learning.pdf",
    "README.md",
    "论文/附件/EI与SCI.png",
    "论文/附件/开源期刊与闭源期刊.png",
    "论文/Research_Trends_in_Application_of_Artificial_Intelligence_in_Alzheimers_Disease_Bibliometric_and_Visualization_Analysis.pdf",
    "论文/附件",
    "未命名.md",
    "论文",
    "杂记",
    "SWPU/925计算机学科综合（数据结构+操作系统）.pdf",
    "SWPU/西南石油大学研究生考试相关.md",
    "SWPU/925考点.md",
    "SWPU/附件/2024分数线.png",
    "SWPU/附件",
    "计算机操作系统.xmind",
    "面向对象程序设计/基类（父类）.md",
    "计算机网络/计算机网络.md",
    "网络安全/信息与网络安全笔记.md",
    "前端/前端学习路线.md",
    "前端/Html5+CSS3.md",
    "Latex学习/Latex公式.md",
    "pytorch/Pytorch基础--以MINIST手写识别为例.md",
    "SCRCU/SCRCU入职考试.md",
    "pytorch/附件/池化层.png",
    "pytorch/附件/激活函数.png",
    "C语言/附件/头插法新建链表流程图.png",
    "C语言/附件/运算优先级.png",
    "区块链/附件/eth1eth2client.png",
    "区块链/附件/account4part.png",
    "未命名.canvas",
    "论文阅读/图片/时间银行分层架构.png"
  ]
}